ifigures/LICENSE
ifigures/__init__.py
ifigures/amoplots.py
ifigures/amoplotsnew.py
ifigures/interact.py
ifigures/latex2png.py
ifigures/my_plots.py
ifigures/timelines.py
ifigures/widgets.py
interactive_publishing-0.1.0.dist-info/LICENSE
interactive_publishing-0.1.0.dist-info/METADATA
interactive_publishing-0.1.0.dist-info/WHEEL
interactive_publishing-0.1.0.dist-info/RECORD
