Metadata-Version: 2.1
Name: interactive-publishing
Version: 0.1.0
Summary: Templates and tools for creating interactive figures and interactive text for publishing in EPUB3/HTML5.
License: BSD-3-Clause license
Author: Nikola Sibalic
Author-email: nikolasibalic@physics.org
Requires-Python: >=3.8,<4.0
Classifier: License :: Other/Proprietary License
Classifier: Programming Language :: Python :: 3
Classifier: Programming Language :: Python :: 3.8
Classifier: Programming Language :: Python :: 3.9
Classifier: Programming Language :: Python :: 3.10
Classifier: Programming Language :: Python :: 3.11
Requires-Dist: Pillow (>=9.4.0,<10.0.0)
Requires-Dist: matplotlib (>=3.6.2,<4.0.0)
Requires-Dist: pngquant (>=1.0.7,<2.0.0)
Requires-Dist: pyvista (>=0.39.1,<0.40.0)
